profanityfilter/__init__.py
profanityfilter/console.py
profanityfilter/profanityfilter.py
profanityfilter/data/badwords.txt
profanityfilter-2.0.6.dist-info/LICENSE
profanityfilter-2.0.6.dist-info/METADATA
profanityfilter-2.0.6.dist-info/WHEEL
profanityfilter-2.0.6.dist-info/entry_points.txt
profanityfilter-2.0.6.dist-info/top_level.txt
profanityfilter-2.0.6.dist-info/RECORD
